discordbotlist/__init__.py
discordbotlist/client.py
discordbotlist/constants.py
discordbotlist_py-1.0.1.dist-info/licenses/LICENSE
discordbotlist_py-1.0.1.dist-info/METADATA
discordbotlist_py-1.0.1.dist-info/WHEEL
discordbotlist_py-1.0.1.dist-info/top_level.txt
discordbotlist_py-1.0.1.dist-info/RECORD
