Metadata-Version: 2.4
Name: discordbotlist-py
Version: 1.0.1
Summary: Easy to use API wrapper for DiscordBotList in Python
Author-email: Rezn1r <rezn1r@proton.me>
License-Expression: MIT
Project-URL: Homepage, https://github.com/Rezn1r/discordbotlist.py
Project-URL: Repository, https://github.com/Rezn1r/discordbotlist.py
Project-URL: Issues, https://github.com/Rezn1r/discordbotlist.py/issues
Classifier: Development Status :: 5 - Production/Stable
Classifier: Intended Audience :: Developers
Classifier: Programming Language :: Python :: 3.12
Classifier: Programming Language :: Python :: 3.13
Classifier: Programming Language :: Python :: 3.14
Classifier: Operating System :: OS Independent
Classifier: Topic :: Software Development :: Libraries
Classifier: Topic :: Utilities
Requires-Python: <=3.14,>=3.12
License-File: LICENSE
Requires-Dist: aiohttp>=3.13.3
Provides-Extra: discord
Requires-Dist: discord>=2.3.2; extra == "discord"
Provides-Extra: pycord
Dynamic: license-file
